reductor/__init__.py
reductor-0.0.1a1.dist-info/METADATA
reductor-0.0.1a1.dist-info/WHEEL
reductor-0.0.1a1.dist-info/licenses/LICENSE.txt
reductor-0.0.1a1.dist-info/RECORD
