Metadata-Version: 2.4
Name: reductor
Version: 0.0.1a1
Project-URL: Documentation, https://github.com/ysenarath/reductor#readme
Project-URL: Issues, https://github.com/ysenarath/reductor/issues
Project-URL: Source, https://github.com/ysenarath/reductor
Author-email: Yasas Senarath <12231659+ysenarath@users.noreply.github.com>
License-Expression: MIT
License-File: LICENSE.txt
Classifier: Development Status :: 4 - Beta
Classifier: Programming Language :: Python
Classifier: Programming Language :: Python :: 3.10
Classifier: Programming Language :: Python :: 3.11
Classifier: Programming Language :: Python :: 3.12
Classifier: Programming Language :: Python :: Implementation :: CPython
Classifier: Programming Language :: Python :: Implementation :: PyPy
Requires-Python: >=3.10
Requires-Dist: datasets>=3.6.0
Requires-Dist: numpy>=2.2.6
Requires-Dist: pandas>=2.3.0
Requires-Dist: sentence-transformers>=4.1.0
Requires-Dist: smolagents>=1.19.0
Requires-Dist: torch>=2.7.1
Requires-Dist: transformers>=4.53.0
